wtforms_dynamic_fields
tests
