Metadata-Version: 1.1
Name: WTForms-Dynamic-Fields
Version: 0.1a3
Summary: Simple wrapper to add "dynamic" (sets of) fields to an already instantiated WTForms form.
Home-page: https://github.com/timusan/wtforms-dynamic-fields
Author: Tim van der Linden
Author-email: tim@shisaa.jp
License: BSD
Platform: any
Classifier: Programming Language :: Python :: 2
Classifier: Programming Language :: Python :: 2.6
Classifier: Programming Language :: Python :: 2.7
Classifier: Programming Language :: Python :: 3
Classifier: Programming Language :: Python :: 3.3
Classifier: Programming Language :: Python :: 3.4
Classifier: Development Status :: 3 - Alpha
Classifier: Natural Language :: English
Classifier: Environment :: Web Environment
Classifier: Intended Audience :: Developers
Classifier: License :: OSI Approved :: BSD License
Classifier: Operating System :: OS Independent
Classifier: Topic :: Software Development :: Libraries :: Python Modules
Classifier: Topic :: Internet :: WWW/HTTP :: Dynamic Content
